imperiums_cli/__init__.py
imperiums_cli/main.py
imp_cli-1.0.2.dist-info/METADATA
imp_cli-1.0.2.dist-info/WHEEL
imp_cli-1.0.2.dist-info/dependency_links.txt
imp_cli-1.0.2.dist-info/entry_points.txt
imp_cli-1.0.2.dist-info/top_level.txt
imp_cli-1.0.2.dist-info/RECORD
